{
    "name": "Mercedes-Benz AMG SL55 Roadster",
    "link": "https://www.carwale.com/mercedes-benz-cars/amg-sl55-roadster/",
    "description": "The price of Mercedes-Benz AMG SL55 Roadster, a 4 seater Convertible, starts from  of Rs. 2.44 Crore. It is available in 1 variant, with an engine of 3982 cc and a choice of 1 transmission: Automatic. AMG SL55 Roadster comes with 10 airbags. Mercedes-Benz AMG SL55 Roadster is available in 3 colours. ",
    "variants": [
        {
            "variant_name": "AMG SL55 Roadster 4MATIC Plus 3982 cc, Petrol, Automatic (TC), 469 bhp",
            "price": "Rs. 2.44 Crore"
        }
    ],
    "on_road_prices": {
        "Delhi": "Rs. 2.80 Crore onwards",
        "Hyderabad": "Rs. 3.01 Crore onwards",
        "Bangalore": "Rs. 3.01 Crore onwards",
        "Mumbai": "Rs. 2.89 Crore onwards",
        "Ahmedabad": "Rs. 2.67 Crore onwards",
        "Kolkata": "Rs. 2.81 Crore onwards",
        "Chennai": "Rs. 3.06 Crore onwards",
        "Pune": "Rs. 2.89 Crore onwards",
        "Lucknow": "Rs. 2.81 Crore onwards"
    },
    "specifications": {
        "Fuel Type": "Petrol",
        "Engine": "3982 cc",
        "Power and Torque": "469 bhp & 700 Nm",
        "DriveTrain": "AWD",
        "Acceleration": "3.9 seconds",
        "Top Speed": "295 kmph"
    }
}